linkml_map/__init__.py
linkml_map/cli/__init__.py
linkml_map/cli/cli.py
linkml_map/compiler/__init__.py
linkml_map/compiler/awk_compiler.py
linkml_map/compiler/compiler.py
linkml_map/compiler/graphviz_compiler.py
linkml_map/compiler/j2_based_compiler.py
linkml_map/compiler/markdown_compiler.py
linkml_map/compiler/python_compiler.py
linkml_map/compiler/r2rml_compiler.py
linkml_map/compiler/sparql_compiler.py
linkml_map/compiler/sql_compiler.py
linkml_map/compiler/sssom_compiler.py
linkml_map/compiler/templates/__init__.py
linkml_map/compiler/templates/markdown.j2
linkml_map/compiler/tr/__init__.py
linkml_map/compiler/tr/transformer_to_mapping_tables.tr.yaml
linkml_map/datamodel/__init__.py
linkml_map/datamodel/sssom.map.yaml
linkml_map/datamodel/transformer_model.py
linkml_map/datamodel/transformer_model.yaml
linkml_map/functions/__init__.py
linkml_map/functions/unit_conversion.py
linkml_map/importer/__init__.py
linkml_map/importer/importer.py
linkml_map/inference/__init__.py
linkml_map/inference/inference.py
linkml_map/inference/inverter.py
linkml_map/inference/schema_mapper.py
linkml_map/session.py
linkml_map/transformer/__init__.py
linkml_map/transformer/duckdb_transformer.py
linkml_map/transformer/object_transformer.py
linkml_map/transformer/transformer.py
linkml_map/utils/__init__.py
linkml_map/utils/dynamic_object.py
linkml_map/utils/eval_utils.py
linkml_map/utils/loaders.py
linkml_map/utils/multi_file_transformer.py
linkml_map-0.3.8.dist-info/METADATA
linkml_map-0.3.8.dist-info/WHEEL
linkml_map-0.3.8.dist-info/entry_points.txt
linkml_map-0.3.8.dist-info/RECORD
